pysera/__init__.py
pysera/_cli.py
pysera/cli/__init__.py
pysera/cli/argument_parser.py
pysera/config/__init__.py
pysera/config/settings.py
pysera/data/__init__.py
pysera/data/data_loader.py
pysera/engine/__init__.py
pysera/engine/deep_features/__init__.py
pysera/engine/deep_features/radiomics_df_extractor.py
pysera/engine/visera_oop/__init__.py
pysera/engine/visera_oop/radiomics_features_extractor.py
pysera/engine/visera_oop/config/__init__.py
pysera/engine/visera_oop/config/materials/__init__.py
pysera/engine/visera_oop/config/materials/bit_mappings.json
pysera/engine/visera_oop/config/materials/feature_modes_mapping.json
pysera/engine/visera_oop/core/__init__.py
pysera/engine/visera_oop/core/base_feature_extractor.py
pysera/engine/visera_oop/core/feature_extraction_manager.py
pysera/engine/visera_oop/core/extractors/__init__.py
pysera/engine/visera_oop/core/extractors/diagnostics_features_extractor.py
pysera/engine/visera_oop/core/extractors/gray_level_cooccurrence_matrix_features_extractor.py
pysera/engine/visera_oop/core/extractors/gray_level_distance_zone_matrix_features_extractor.py
pysera/engine/visera_oop/core/extractors/gray_level_run_length_matrix_features_extractor.py
pysera/engine/visera_oop/core/extractors/gray_level_size_zone_matrix_features_extractor.py
pysera/engine/visera_oop/core/extractors/intensity_histogram_features_extractor.py
pysera/engine/visera_oop/core/extractors/intensity_peak_features_extractor.py
pysera/engine/visera_oop/core/extractors/intensity_volume_histogram_features_extractor.py
pysera/engine/visera_oop/core/extractors/moment_invariants_features_extractor.py
pysera/engine/visera_oop/core/extractors/morphological_features_extractor.py
pysera/engine/visera_oop/core/extractors/neighborhood_gray_level_dependence_matrix_features_extractor.py
pysera/engine/visera_oop/core/extractors/neighbourhood_gray_tone_difference_matrix_features_extractor.py
pysera/engine/visera_oop/core/extractors/statistics_features_extractor.py
pysera-2.1.3.dist-info/licenses/LICENSE
pysera-2.1.3.dist-info/METADATA
pysera-2.1.3.dist-info/WHEEL
pysera-2.1.3.dist-info/entry_points.txt
pysera-2.1.3.dist-info/top_level.txt
pysera-2.1.3.dist-info/RECORD
