Metadata-Version: 2.4
Name: pysera
Version: 2.1.3
Summary: A Python library for radiomics feature extraction with multiprocessing support
Home-page: https://github.com/Tecvico/PySERA
Author: Dr. Mohammad R. Salmanpour, A.H. Pouria
Author-email: "Dr. Mohammad R. Salmanpour" <M.salmanpoor66@gmail.com>, Amir Hossein Pouria <amirporia99.1378@gmail.com>, Mehrdad Oveisi <moveisi@cs.ubc.ca>, Arman Rahmim <arman.rahmim@ubc.ca>
Maintainer-email: "Dr. Mohammad R. Salmanpour" <M.salmanpoor66@gmail.com>, "A.H. Pouria" <amirporia99.1378@gmail.com>
License-Expression: MIT
Project-URL: Homepage, https://github.com/Tecvico/PySERA
Project-URL: Documentation, https://pysera.readthedocs.io/
Project-URL: Repository, https://github.com/Tecvico/PySERA.git
Project-URL: Bug Reports, https://github.com/Tecvico/PySERA/issues
Keywords: medical-imaging,Standardized-Radiomics-Feature-Extraction,Quantitative-Analysis,IBSI-Standardization,healthcare
Classifier: Development Status :: 5 - Production/Stable
Classifier: Intended Audience :: Science/Research
Classifier: Intended Audience :: Healthcare Industry
Classifier: Topic :: Scientific/Engineering :: Medical Science Apps.
Classifier: Topic :: Scientific/Engineering :: Image Processing
Classifier: Programming Language :: Python :: 3.10
Classifier: Programming Language :: Python :: 3.11
Classifier: Operating System :: OS Independent
Requires-Python: >=3.10
License-File: LICENSE
Requires-Dist: numpy>=2.0.0
Requires-Dist: pandas>=2.3.1
Requires-Dist: scikit-learn>=1.7
Requires-Dist: SimpleITK>=2.5.2
Requires-Dist: opencv-python>=4.11.0.86
Requires-Dist: nibabel>=5.3.2
Requires-Dist: pydicom>=3.0.1
Requires-Dist: scikit-image>=0.25.2
Requires-Dist: openpyxl>=3.1.5
Requires-Dist: pynrrd>=1.1.3
Requires-Dist: psutil>=7.0.0
Requires-Dist: scipy>=1.15.3
Requires-Dist: Pillow>=11.3.0
Requires-Dist: rt-utils>=1.2.7
Requires-Dist: connected-components-3d>=3.25.0
Provides-Extra: dev
Requires-Dist: pytest>=7.0; extra == "dev"
Requires-Dist: pytest-cov>=4.0; extra == "dev"
Requires-Dist: black>=23.0; extra == "dev"
Requires-Dist: flake8>=6.0; extra == "dev"
Requires-Dist: mypy>=1.0; extra == "dev"
Dynamic: author
Dynamic: home-page
Dynamic: license-file
Dynamic: requires-python
